{
  "basics": {
    "name": "Marissa Halim",
    "label": "Student",
    "picture": "https://marissahalim.github.io/images/marissalh.jpg",
    "email": "mhalim@hawaii.edu",
    "phone": "808-724-2324",
    "website": "https://marissahalim.github.io",
    "summary": "I am studying for a B.S. in Computer Science in the Department of Information and Computer Sciences at the University of Hawaii. I am also hoping to double major in Computer Animation in the Academy for Creative Media at the University of Hawaii. I expect to graduate in Spring, 2023.",
    "location": {
      "address": "",
      "postalCode": "96822",
      "city": "Honolulu",
      "countryCode": "USA",
      "region": "Hawaii"
    },
    "profiles": [
      {
        "network": "github",
        "username": "marissahalim",
        "url": "http://github.com/marissahalim"
      },
      {
        "network": "linkedin",
        "username": "marissahalim",
        "url": "http://linkedin.com/in/marissalhalim"
      },
      {
        "network": "instagram",
        "username": "_marissahalim",
        "url": "http://instagram.com/_marissahalim/"
      }
    ]
  },
  "interests": [
    {
      "name": "video game design",
      "keywords": [
      ]
    },
    {
      "name": "web design/development",
      "keywords": [
      ]
    },
    {
      "name": "animation",
      "keywords": [
      ]
    },
    {
      "name": "character design",
      "keywords": [
      ]
    }
  ],
  "skills": [
    {
      "name": "Languages and Frameworks",
      "level": "",
      "keywords": [
        "C",
        "C++",
        "Java",
        "Javascript"
      ]
    },
    {
      "name": "Toolsets/OS",
      "level": "",
      "keywords": [
        "Windows 10",
        "Git/GitHub",
        "g++"
      ]
    },
     {
      "name": "Applications",
      "level": "",
      "keywords": [
        "Adobe Photoshop",
        "Adobe Illustrator"
      ]
    }
  ],
  "education": [
    {
      "institution": "University of Hawaii, Honolulu, HI",
      "area": "Computer Science (expected Spring, 2023)",
      "studyType": "B.S.",
      "startDate": "2019-08-26",
      "endDate": "Present",
      "gpa": "",
      "courses": [
      ]
    }
  ],
  "work": [
    {
      "company": "Group 70, International",
      "position": "Accounting Intern",
      "website": "",
      "startDate": "2019-03-18",
      "endDate": "Present",
      "summary": "Help the accounting department",
      "highlights": [
        "Input invoice data into an Excel sheet to keep track of when and what expenses were paid",
        "File and organize all documented communication for current and future projects"
      ]
    }
  ],
  "volunteer": [
    {
      "organization": "Seamsters Union",
      "website": "https://nomoola.com/seamsters-union/",
      "position": "Volunteer",
      "startDate": "2020-07-01",
      "endDate": "Present",
      "summary": "Make masks from upcycled products for Hawaii’s most needy population",
      "highlights": [
        "Cut face pieces and ties for adult and keiki masks",
        "Organization donated over 7,000 masks to numerous organizations around the nation"
      ]
    }
  ],
  "awards": [
    {
      "title": "Manoa Academic Merit Scholarship",
      "date": "2019-Present",
      "awarder": "University of Hawaii at Manoa",
      "summary": "Awarded to students that fall within the 3.5 GPA range or higher."
    }
  ],
  "references": [
    {
      "name": "Available upon request",
      "reference": ""
    }
  ]
}
